open_api_apimatic-1.0.0.dist-info/licenses/LICENSE
openai/__init__.py
openai/api_helper.py
openai/configuration.py
openai/openai_client.py
openai/controllers/__init__.py
openai/controllers/base_controller.py
openai/controllers/completions_controller.py
openai/controllers/edits_controller.py
openai/controllers/embeddings_controller.py
openai/controllers/engines_controller.py
openai/controllers/files_controller.py
openai/controllers/fine_tunes_controller.py
openai/controllers/images_controller.py
openai/controllers/models_controller.py
openai/controllers/moderations_controller.py
openai/exceptions/__init__.py
openai/exceptions/api_exception.py
openai/http/__init__.py
openai/http/http_call_back.py
openai/http/http_method_enum.py
openai/http/http_request.py
openai/http/http_response.py
openai/http/auth/__init__.py
openai/http/auth/o_auth_2.py
openai/models/__init__.py
openai/models/categories.py
openai/models/category_scores.py
openai/models/choice.py
openai/models/choice_1.py
openai/models/create_completion_request.py
openai/models/create_edit.py
openai/models/create_edit_request.py
openai/models/create_embeddings.py
openai/models/create_embeddings_request.py
openai/models/create_fine_tune_request.py
openai/models/create_image.py
openai/models/create_image_request.py
openai/models/create_moderation.py
openai/models/create_moderation_request.py
openai/models/datum.py
openai/models/datum_1.py
openai/models/datum_2.py
openai/models/datum_3.py
openai/models/list_engines.py
openai/models/list_fine_tunes.py
openai/models/list_models.py
openai/models/ok.py
openai/models/permission.py
openai/models/result.py
openai/models/retrieve_engine.py
openai/models/retrieve_model.py
openai/models/usage.py
openai/models/usage_1.py
openai/utilities/__init__.py
openai/utilities/file_wrapper.py
open_api_apimatic-1.0.0.dist-info/METADATA
open_api_apimatic-1.0.0.dist-info/WHEEL
open_api_apimatic-1.0.0.dist-info/top_level.txt
open_api_apimatic-1.0.0.dist-info/RECORD
